{
  "fetched_at": "2026-05-28T09:49:57.533212+00:00",
  "river_flow": [
    {
      "station_name": "Garissa Bridge (WRA)",
      "latitude": -0.4532,
      "longitude": 39.6461,
      "water_level_m": 3.16,
      "flood_threshold_m": 4.5,
      "discharge_m3s": 320.7,
      "status": "Alert",
      "updated_at": "2026-05-28T03:49:57.533212+00:00"
    }
  ],
  "vegetation_health": [
    {
      "county": "Garissa County",
      "latitude": -0.45,
      "longitude": 39.65,
      "vci_score": 57.7,
      "status": "Normal",
      "updated_at": "2026-05-26T09:49:57.533212+00:00"
    },
    {
      "county": "Tana River County",
      "latitude": -1.5,
      "longitude": 40.0,
      "vci_score": 53.0,
      "status": "Normal",
      "updated_at": "2026-05-26T09:49:57.533212+00:00"
    },
    {
      "county": "Kitui County",
      "latitude": -1.36,
      "longitude": 38.01,
      "vci_score": 26.2,
      "status": "Severe Drought",
      "updated_at": "2026-05-28T09:49:57.533212+00:00"
    }
  ],
  "headwater_health": {
    "region": "Upper Basin (Nyeri/Nyandarua)",
    "latitude": -0.41,
    "longitude": 36.95,
    "forest_cover_pct": 22.6,
    "streamflow_trend": "Stable",
    "deforestation_alerts": 4,
    "updated_at": "2026-05-23T09:49:57.533212+00:00"
  },
  "biodiversity": [
    {
      "species": "Elephant (Route 13)",
      "tracked_individuals": 29,
      "location_cluster": {
        "latitude": -0.9373,
        "longitude": 39.1177
      },
      "movement_status": "Migrating South",
      "updated_at": "2026-05-28T08:49:57.533212+00:00"
    },
    {
      "species": "Hirola Antelope",
      "tracked_individuals": 61,
      "location_cluster": {
        "latitude": -1.3102,
        "longitude": 40.1833
      },
      "movement_status": "Grazing (Protected Area)",
      "updated_at": "2026-05-28T09:49:57.533212+00:00"
    }
  ],
  "economic_value": {
    "livestock_offtake_daily": 1020,
    "average_price_kes": 37116,
    "cold_chain_nodes_active": 12,
    "solar_uptime_pct": 95.9,
    "updated_at": "2026-05-28T09:49:57.533212+00:00"
  },
  "governance": {
    "ccri_grants_allocated_kes": 9214855,
    "cfa_restructuring_status": "Phase 1 Complete",
    "active_community_forest_associations": 24,
    "updated_at": "2026-05-19T09:49:57.533212+00:00"
  },
  "warm_data": {
    "source": "Somali Indigenous Oracles (Council of Elders)",
    "seasonal_forecast": "High likelihood of flash floods in lower basin; move livestock to higher ground.",
    "community_sentiment": "Preparing Action",
    "updated_at": "2026-05-09T09:49:57.533212+00:00"
  }
}